{
  "platform": "android",
  "appName": "BusIsComing",
  "applicationId": "com.example.busiscoming",
  "versionName": "1.0",
  "versionCode": 1,
  "fileName": "BusIsComing.apk",
  "relativePath": "BusIsComing.apk",
  "sourcePath": "/Users/jianglijie/AndroidStudioProjects/BusIsComming/app/release/app-release.apk",
  "sizeBytes": 5610777,
  "sizeLabel": {
    "zh-Hant": "約 5.4 MB",
    "zh-Hans": "约 5.4 MB",
    "en": "About 5.4 MB"
  },
  "sha256": "400a55622e8ca38bd3a6b8bbe4329a94c90f688c2a5f524a45c8cc857c43f55b",
  "lastUpdated": "2026-06-26",
  "status": "available"
}
